{
  "notes": [
    {
      "id": 1758689285088.412,
      "x": 28.47298289020881,
      "y": 144.24262940338718,
      "text": "New Note",
      "colorIdx": 2,
      "width": 130,
      "height": 90
    },
    {
      "id": 1758689293209.92,
      "x": -332.4954963223866,
      "y": 169.69648664541842,
      "text": "New Note",
      "colorIdx": 3,
      "width": 130,
      "height": 90
    },
    {
      "id": 1758689310187.814,
      "x": -156.67074076826646,
      "y": -92.60823913585895,
      "text": "New Note",
      "colorIdx": 0,
      "width": 130,
      "height": 90
    },
    {
      "x": -772.071818945394,
      "y": 1.0849330230969656,
      "text": "hello my friend",
      "colorIdx": 3,
      "width": 130,
      "height": 90,
      "id": 1758689771138.0725
    },
    {
      "x": -458.1278749938982,
      "y": -236.44127234779802,
      "text": "hey bro",
      "colorIdx": 2,
      "width": 130,
      "height": 90,
      "id": 1758691859658.8296
    },
    {
      "x": -815.6353820425612,
      "y": -212.97653933287017,
      "text": "New Note",
      "colorIdx": 2,
      "width": 130,
      "height": 90,
      "id": 1758691873076.6885
    }
  ],
  "yarns": [
    {
      "fromType": "note",
      "from": 1758689293209.92,
      "toType": "note",
      "to": 1758689285088.412
    },
    {
      "fromType": "note",
      "from": 1758689310187.814,
      "toType": "note",
      "to": 1758689293209.92
    },
    {
      "fromType": "note",
      "from": 1758689771138.0725,
      "toType": "note",
      "to": 1758689293209.92
    },
    {
      "fromType": "note",
      "from": 1758691859658.8296,
      "toType": "note",
      "to": 1758689771138.0725
    }
  ],
  "polaroids": [],
  "viewOffset": {
    "x": 975,
    "y": 304
  },
  "noteScale": 1,
  "zoom": 1
}